nitpick/__init__.py
nitpick/__main__.py
nitpick/blender.py
nitpick/cli.py
nitpick/compat.py
nitpick/config.py
nitpick/constants.py
nitpick/core.py
nitpick/exceptions.py
nitpick/fields.py
nitpick/flake8.py
nitpick/generic.py
nitpick/plugins/__init__.py
nitpick/plugins/base.py
nitpick/plugins/info.py
nitpick/plugins/ini.py
nitpick/plugins/json.py
nitpick/plugins/text.py
nitpick/plugins/toml.py
nitpick/plugins/yaml.py
nitpick/resources/__init__.py
nitpick/resources/any/__init__.py
nitpick/resources/any/codeclimate.toml
nitpick/resources/any/commitizen.toml
nitpick/resources/any/commitlint.toml
nitpick/resources/any/editorconfig.toml
nitpick/resources/any/git-legal.toml
nitpick/resources/any/pre-commit-hooks.toml
nitpick/resources/any/prettier.toml
nitpick/resources/javascript/__init__.py
nitpick/resources/javascript/package-json.toml
nitpick/resources/kotlin/__init__.py
nitpick/resources/kotlin/ktlint.toml
nitpick/resources/markdown/__init__.py
nitpick/resources/markdown/markdownlint.toml
nitpick/resources/presets/__init__.py
nitpick/resources/presets/nitpick.toml
nitpick/resources/proto/__init__.py
nitpick/resources/proto/protolint.toml
nitpick/resources/python/310.toml
nitpick/resources/python/311.toml
nitpick/resources/python/312.toml
nitpick/resources/python/313.toml
nitpick/resources/python/314.toml
nitpick/resources/python/__init__.py
nitpick/resources/python/absent.toml
nitpick/resources/python/autoflake.toml
nitpick/resources/python/bandit.toml
nitpick/resources/python/black.toml
nitpick/resources/python/flake8.toml
nitpick/resources/python/github-workflow.toml
nitpick/resources/python/ipython.toml
nitpick/resources/python/isort.toml
nitpick/resources/python/mypy.toml
nitpick/resources/python/poetry-editable.toml
nitpick/resources/python/poetry-venv.toml
nitpick/resources/python/poetry.toml
nitpick/resources/python/pre-commit-hooks.toml
nitpick/resources/python/pylint.toml
nitpick/resources/python/radon.toml
nitpick/resources/python/readthedocs.toml
nitpick-0.38.0.dist-info/METADATA
nitpick-0.38.0.dist-info/WHEEL
nitpick-0.38.0.dist-info/entry_points.txt
nitpick-0.38.0.dist-info/licenses/AUTHORS.rst
nitpick-0.38.0.dist-info/licenses/LICENSE
nitpick-0.38.0.dist-info/RECORD
