Metadata-Version: 2.4
Name: nitpick
Version: 0.38.0
Summary: Enforce the same settings across multiple language-independent projects
License: MIT
License-File: AUTHORS.rst
License-File: LICENSE
Keywords: flake8,linter,python3,styleguide
Author: W. Augusto Andreoli
Author-email: andreoliwa@gmail.com
Requires-Python: >=3.10,<4.0
Classifier: Development Status :: 4 - Beta
Classifier: Environment :: Plugins
Classifier: Intended Audience :: Developers
Classifier: License :: OSI Approved :: MIT License
Classifier: Operating System :: MacOS
Classifier: Operating System :: Unix
Classifier: Programming Language :: Python :: 3
Classifier: Programming Language :: Python :: 3.10
Classifier: Programming Language :: Python :: 3.11
Classifier: Programming Language :: Python :: 3.12
Classifier: Programming Language :: Python :: 3.13
Classifier: Programming Language :: Python :: 3.14
Classifier: Programming Language :: Python :: 3 :: Only
Classifier: Topic :: Software Development :: Quality Assurance
Provides-Extra: doc
Provides-Extra: lint
Provides-Extra: test
Requires-Dist: ConfigUpdater
Requires-Dist: StrEnum
Requires-Dist: attrs (>=20.1.0)
Requires-Dist: autorepr
Requires-Dist: click
Requires-Dist: dictdiffer
Requires-Dist: dpath
Requires-Dist: flake8 (>=3.0.0)
Requires-Dist: flatten-dict
Requires-Dist: freezegun (>=1.5.2) ; extra == "test"
Requires-Dist: furl
Requires-Dist: gitignore_parser
Requires-Dist: identify
Requires-Dist: jmespath
Requires-Dist: loguru
Requires-Dist: marshmallow (>=3.0.0b10)
Requires-Dist: marshmallow-polyfield (>=5.10,<6.0)
Requires-Dist: more-itertools
Requires-Dist: packaging
Requires-Dist: pluggy
Requires-Dist: pylint ; extra == "lint"
Requires-Dist: pytest ; extra == "test"
Requires-Dist: pytest-cov ; extra == "test"
Requires-Dist: pytest-datadir ; extra == "test"
Requires-Dist: pytest-socket ; extra == "test"
Requires-Dist: pytest-testmon ; extra == "test"
Requires-Dist: pytest-watch ; extra == "test"
Requires-Dist: python-slugify
Requires-Dist: requests
Requires-Dist: requests-cache (>=1.0.0)
Requires-Dist: responses ; extra == "test"
Requires-Dist: ruamel-yaml-clib (>=0.2.12)
Requires-Dist: ruamel.yaml
Requires-Dist: sortedcontainers
Requires-Dist: sphinx ; extra == "doc"
Requires-Dist: sphinx-gitref ; extra == "doc"
Requires-Dist: sphinx_rtd_theme ; extra == "doc"
Requires-Dist: sphobjinv ; extra == "doc"
Requires-Dist: testfixtures ; extra == "test"
Requires-Dist: toml
Requires-Dist: tomlkit (>=0.8.0)
Project-URL: Changelog, https://github.com/andreoliwa/nitpick/blob/develop/CHANGELOG.md
Project-URL: Documentation, https://nitpick.rtfd.io/
Project-URL: Issue Tracker, https://github.com/andreoliwa/nitpick/issues
Project-URL: Repository, https://github.com/andreoliwa/nitpick
